main.py
object.py
settings.py
yonghu.py
yonghu2.py
BomberKillers-0.0.3.dist-info/METADATA
BomberKillers-0.0.3.dist-info/WHEEL
BomberKillers-0.0.3.dist-info/top_level.txt
BomberKillers-0.0.3.dist-info/RECORD
